celery_abc/__init__.py
celery_abc/caller.py
celery_abc/worker.py
celery_abc-0.0.1.dist-info/LICENCE
celery_abc-0.0.1.dist-info/METADATA
celery_abc-0.0.1.dist-info/WHEEL
celery_abc-0.0.1.dist-info/top_level.txt
celery_abc-0.0.1.dist-info/RECORD
