Metadata-Version: 2.1
Name: celery-abc
Version: 0.0.1
Summary: Create microservices with celery and abstract interfaces.
Home-page: https://github.com/GreenBlackSky/celery-abc
Author: Mikhail Khimukhin
Author-email: greenblacksky@gmail.com
License: UNKNOWN
Project-URL: Bug Tracker, https://github.com/GreenBlackSky/celery-abc/issues
Platform: UNKNOWN
Classifier: Programming Language :: Python :: 3
Classifier: License :: OSI Approved :: MIT License
Classifier: Operating System :: OS Independent
Requires-Python: >=3.9
License-File: LICENCE
